setup.py
src/__init__.py
src/yacontracts.py
src/yacontracts.egg-info/PKG-INFO
src/yacontracts.egg-info/SOURCES.txt
src/yacontracts.egg-info/dependency_links.txt
src/yacontracts.egg-info/requires.txt
src/yacontracts.egg-info/top_level.txt